modelsignature/__init__.py
modelsignature/auth.py
modelsignature/client.py
modelsignature/constants.py
modelsignature/exceptions.py
modelsignature/identity.py
modelsignature/models.py
modelsignature/py.typed
modelsignature/embedding/__init__.py
modelsignature/embedding/cli.py
modelsignature/embedding/core.py
modelsignature/embedding/dataset_generator.py
modelsignature/embedding/evaluator.py
modelsignature/embedding/trainer.py
modelsignature/embedding/utils.py
modelsignature-0.3.0.dist-info/licenses/LICENSE
modelsignature-0.3.0.dist-info/METADATA
modelsignature-0.3.0.dist-info/WHEEL
modelsignature-0.3.0.dist-info/entry_points.txt
modelsignature-0.3.0.dist-info/top_level.txt
modelsignature-0.3.0.dist-info/RECORD
