Metadata-Version: 2.4
Name: modelsignature
Version: 0.3.0
Summary: Cryptographic identity verification for AI models — like SSL certificates for AI conversations
Author-email: ModelSignature Team <team@modelsignature.com>
Maintainer-email: ModelSignature Team <team@modelsignature.com>
License: MIT
Project-URL: Homepage, https://modelsignature.com
Project-URL: Documentation, https://docs.modelsignature.com
Project-URL: Repository, https://github.com/ModelSignature/python-sdk
Project-URL: Bug Tracker, https://github.com/ModelSignature/python-sdk/issues
Project-URL: Changelog, https://github.com/ModelSignature/python-sdk/blob/main/CHANGELOG.md
Keywords: ai,ml,verification,cryptography,identity,llm,chatbot
Classifier: Development Status :: 4 - Beta
Classifier: Intended Audience :: Developers
Classifier: Operating System :: OS Independent
Classifier: Programming Language :: Python :: 3
Classifier: Programming Language :: Python :: 3.8
Classifier: Programming Language :: Python :: 3.9
Classifier: Programming Language :: Python :: 3.10
Classifier: Programming Language :: Python :: 3.11
Classifier: Programming Language :: Python :: 3.12
Classifier: Topic :: Internet :: WWW/HTTP
Classifier: Topic :: Security :: Cryptography
Classifier: Topic :: Scientific/Engineering :: Artificial Intelligence
Classifier: Topic :: Software Development :: Libraries :: Python Modules
Classifier: Typing :: Typed
Requires-Python: >=3.8
License-File: LICENSE
Requires-Dist: requests>=2.28.0
Provides-Extra: dev
Requires-Dist: pytest>=7.0.0; extra == "dev"
Requires-Dist: pytest-mock>=3.10.0; extra == "dev"
Requires-Dist: pytest-cov>=4.0.0; extra == "dev"
Requires-Dist: black>=23.0.0; extra == "dev"
Requires-Dist: isort>=5.12.0; extra == "dev"
Requires-Dist: flake8>=6.0.0; extra == "dev"
Requires-Dist: mypy>=1.0.0; extra == "dev"
Requires-Dist: types-requests>=2.28.0; extra == "dev"
Provides-Extra: test
Requires-Dist: pytest>=7.0.0; extra == "test"
Requires-Dist: pytest-mock>=3.10.0; extra == "test"
Requires-Dist: pytest-cov>=4.0.0; extra == "test"
Provides-Extra: embedding
Requires-Dist: torch>=2.0.0; extra == "embedding"
Requires-Dist: transformers>=4.35.0; extra == "embedding"
Requires-Dist: peft>=0.7.0; extra == "embedding"
Requires-Dist: datasets>=2.14.0; extra == "embedding"
Requires-Dist: accelerate>=0.24.0; extra == "embedding"
Requires-Dist: bitsandbytes>=0.41.0; extra == "embedding"
Requires-Dist: huggingface-hub>=0.17.0; extra == "embedding"
Requires-Dist: tqdm>=4.65.0; extra == "embedding"
Dynamic: license-file
